LICENSE.txt
MANIFEST.in
README.rst
setup.cfg
setup.py
fastapi_ses/__init__.py
fastapi_ses/fastses.py
fastapi_ses/message.py
fastapi_ses.egg-info/PKG-INFO
fastapi_ses.egg-info/SOURCES.txt
fastapi_ses.egg-info/dependency_links.txt
fastapi_ses.egg-info/top_level.txt