Metadata-Version: 2.1
Name: fastapi-ses
Version: 1.0.0
Summary: A simple FastAPI email library for Amazon's Simple Email Service
Home-page: https://github.com/ajitjasrotia/fastapi-ses
Author: Ajit Jasrotia
Author-email: ajitjasrotia012@gmail.com
License: MIT License
Platform: UNKNOWN
Classifier: Development Status :: 5 - Production/Stable
Classifier: Intended Audience :: Developers
Classifier: License :: OSI Approved :: MIT License
Classifier: Operating System :: OS Independent
Classifier: Programming Language :: Python :: 3
Classifier: Programming Language :: Python :: 3.6
Classifier: Programming Language :: Python :: 3.7
Classifier: Programming Language :: Python :: 3.8
Classifier: Programming Language :: Python :: 3.9
Classifier: Programming Language :: Python :: 3.10
Classifier: Programming Language :: Python :: 3.11
Classifier: Topic :: Utilities
License-File: LICENSE.txt
